<annotation>
	<folder>JPEGImages</folder>
	<filename>010028.jpg</filename>
	<path>C:\Users\Aviuh\Desktop\Robot\JPEGImages\010028.jpg</path>
	<source>
		<database>Unknown</database>
	</source>
	<size>
		<width>309</width>
		<height>336</height>
		<depth>3</depth>
	</size>
	<segmented>0</segmented>
	<object>
		<name>robot</name>
		<pose>Unspecified</pose>
		<truncated>0</truncated>
		<difficult>0</difficult>
		<bndbox>
			<xmin>62</xmin>
			<ymin>47</ymin>
			<xmax>247</xmax>
			<ymax>318</ymax>
		</bndbox>
	</object>
</annotation>
